cdk_sops_secrets/__init__.py
cdk_sops_secrets/py.typed
cdk_sops_secrets/_jsii/__init__.py
cdk_sops_secrets/_jsii/cdk-sops-secrets@2.4.3.jsii.tgz
cdk_sops_secrets-2.4.3.dist-info/LICENSE
cdk_sops_secrets-2.4.3.dist-info/METADATA
cdk_sops_secrets-2.4.3.dist-info/WHEEL
cdk_sops_secrets-2.4.3.dist-info/top_level.txt
cdk_sops_secrets-2.4.3.dist-info/RECORD
